storage_bridge/__init__.py
storage_bridge/asynchro/__init__.py
storage_bridge/asynchro/local.py
storage_bridge/sync/__init__.py
storage_bridge/sync/local.py
storage_bridge/sync/s3.py
storage_bridge/typeclass/__init__.py
storage_bridge/typeclass/asyncstorage.py
storage_bridge/typeclass/storage.py
storage_bridge-0.1.3.dist-info/METADATA
storage_bridge-0.1.3.dist-info/WHEEL
storage_bridge-0.1.3.dist-info/top_level.txt
storage_bridge-0.1.3.dist-info/RECORD
