Metadata-Version: 2.2
Name: storage-bridge
Version: 0.1.3
Summary: A Python package for managing storage
Home-page: https://github.com/yourusername/storage-bridge
Author: Jacob Vartuli-Schonberg
Author-email: jacob.vartuli.schonberg@gmail.com
Classifier: Programming Language :: Python :: 3
Classifier: License :: OSI Approved :: MIT License
Classifier: Operating System :: OS Independent
Requires-Python: >=3.9
Requires-Dist: boto3==1.35.90
Requires-Dist: botocore==1.35.90
Requires-Dist: build==1.2.2.post1
Requires-Dist: jmespath==1.0.1
Requires-Dist: packaging==24.2
Requires-Dist: pyproject_hooks==1.2.0
Requires-Dist: python-dateutil==2.9.0.post0
Requires-Dist: s3transfer==0.10.4
Requires-Dist: six==1.17.0
Requires-Dist: urllib3
Dynamic: author
Dynamic: author-email
Dynamic: classifier
Dynamic: description
Dynamic: description-content-type
Dynamic: home-page
Dynamic: requires-dist
Dynamic: requires-python
Dynamic: summary
